.hgignore
.hgtags
CHANGES.txt
LICENSE.txt
MANIFEST.in
README.txt
bootstrap.py
buildout.cfg
setup.py
js/__init__.py
js.strophe.egg-info/PKG-INFO
js.strophe.egg-info/SOURCES.txt
js.strophe.egg-info/dependency_links.txt
js.strophe.egg-info/entry_points.txt
js.strophe.egg-info/namespace_packages.txt
js.strophe.egg-info/not-zip-safe
js.strophe.egg-info/requires.txt
js.strophe.egg-info/top_level.txt
js/strophe/__init__.py
js/strophe/test_strophe.js.txt
js/strophe/resources/strophe.js
js/strophe/resources/strophe.min.js