Metadata-Version: 1.0
Name: js.strophe
Version: 1.1.3
Summary: Fanstatic packaging of Strophe.js
Home-page: UNKNOWN
Author: Fanstatic Developers
Author-email: fanstatic@googlegroups.com
License: BSD
Platform: UNKNOWN
